appromath/__init__.py
appromath/code.py
appromath-1.1.0.dist-info/LICENSE
appromath-1.1.0.dist-info/METADATA
appromath-1.1.0.dist-info/WHEEL
appromath-1.1.0.dist-info/top_level.txt
appromath-1.1.0.dist-info/RECORD
